{"language":"de","graph_title":"Anzahl der PV-Anlagen auf bezirkseigenen Geb\u00e4uden","page_content":"\nDer Indikator zeigt die Anzahl der Photovoltaikanlagen (PV-Anlagen) auf bezirkseigenen Geb\u00e4uden.\n","national_metadata_updated_date":"2022-11-17","national_data_updated_date":"2022-11-17","national_metadata_update_url_text":"2022-11-17: see changes on GitHub","national_metadata_update_url":"https://github.com/DrJannisHoek/sdg-enz-staging-data/commit/fef30660556194270be874fc44ac9184937aad8f","national_data_update_url_text":"2022-11-17: see changes on GitHub","national_data_update_url":"https://github.com/DrJannisHoek/sdg-enz-staging-data/commit/fef30660556194270be874fc44ac9184937aad8f","indicator":"7.1.c","target_id":"7.1","sdg_goal":"7","reporting_status":"complete","data_non_statistical":false,"graph_type":"line","indicator_sort_order":"07-01-0c","indicator_name":"J\u00e4hrliche Einsparung/ Absenkpfad"}